sspic/__init__.py
sspic/_credential.py
sspic/_filetime.py
sspic/_sec_context.py
sspic/py.typed
sspic/raw/__init__.py
sspic/raw/_context_attributes.cp311-win32.pyd
sspic/raw/_context_attributes.pyi
sspic/raw/_credential.cp311-win32.pyd
sspic/raw/_credential.pyi
sspic/raw/_credential_attributes.cp311-win32.pyd
sspic/raw/_credential_attributes.pyi
sspic/raw/_message.cp311-win32.pyd
sspic/raw/_message.pyi
sspic/raw/_ntstatus.cp311-win32.pyd
sspic/raw/_ntstatus.pyi
sspic/raw/_security_buffer.cp311-win32.pyd
sspic/raw/_security_buffer.pyi
sspic/raw/_security_context.cp311-win32.pyd
sspic/raw/_security_context.pyi
sspic/raw/_security_package.cp311-win32.pyd
sspic/raw/_security_package.pyi
sspic/raw/_text.cp311-win32.pyd
sspic/raw/_winerror.py
sspic-0.1.0.dist-info/LICENSE
sspic-0.1.0.dist-info/METADATA
sspic-0.1.0.dist-info/WHEEL
sspic-0.1.0.dist-info/top_level.txt
sspic-0.1.0.dist-info/RECORD
